Genesis_PyAPI-1.2.1.dist-info/DESCRIPTION.rst
Genesis_PyAPI-1.2.1.dist-info/METADATA
Genesis_PyAPI-1.2.1.dist-info/RECORD
Genesis_PyAPI-1.2.1.dist-info/WHEEL
Genesis_PyAPI-1.2.1.dist-info/metadata.json
Genesis_PyAPI-1.2.1.dist-info/top_level.txt
genesis/__init__.py
genesis/data.py
genesis/genesis.py
genesis/project.py
genesis/utils.py
genesis/tests/test_login.py
