Metadata-Version: 2.0
Name: Genesis-PyAPI
Version: 1.2.1
Summary: Python API for the Genesis platform.
Home-page: https://github.com/genialis/genesis-pyapi/
Author: Genialis, Inc.
Author-email: dev-team@genialis.com
License: Apache License (2.0)
Platform: UNKNOWN
Classifier: Development Status :: 4 - Beta
Classifier: Environment :: Console
Classifier: Intended Audience :: Developers
Classifier: License :: OSI Approved :: Apache Software License
Classifier: Operating System :: OS Independent
Classifier: Programming Language :: Python
Classifier: Programming Language :: Python :: 2
Classifier: Programming Language :: Python :: 2.7
Classifier: Programming Language :: Python :: 3
Classifier: Programming Language :: Python :: 3.3
Classifier: Programming Language :: Python :: 3.4
Classifier: Topic :: Software Development :: Libraries :: Python Modules
Requires-Dist: requests (>=2.6.0)
Requires-Dist: slumber (>=0.7.1)
Provides-Extra: docs
Requires-Dist: sphinx (>=1.7.0); extra == 'docs'
